torchslide/__init__.py
torchslide/iconv.dll
torchslide/libcairo-2.dll
torchslide/libffi-6.dll
torchslide/libgdk_pixbuf-2.0-0.dll
torchslide/libgio-2.0-0.dll
torchslide/libglib-2.0-0.dll
torchslide/libgmodule-2.0-0.dll
torchslide/libgobject-2.0-0.dll
torchslide/libintl-8.dll
torchslide/libjpeg-62.dll
torchslide/libopenjp2.dll
torchslide/libopenslide-0.dll
torchslide/libpixman-1-0.dll
torchslide/libpng16-16.dll
torchslide/libsqlite3-0.dll
torchslide/libtiff-5.dll
torchslide/libxml2-2.dll
torchslide/openjp2.dll
torchslide/tiff.dll
torchslide/torchslide.cp37-win_amd64.pyd
torchslide/zlib1.dll
torchslide_any-0.3.0.dist-info/LICENSE
torchslide_any-0.3.0.dist-info/METADATA
torchslide_any-0.3.0.dist-info/WHEEL
torchslide_any-0.3.0.dist-info/top_level.txt
torchslide_any-0.3.0.dist-info/RECORD
