Metadata-Version: 2.1
Name: torchslide-any
Version: 0.3.0
Summary: torchslide-any - source version of torchslide for Python 3.6+
Home-page: https://github.com/arquolo/torchslide
Author: Paul Maevskikh
Author-email: arquolo@gmail.com
License: UNKNOWN
Platform: UNKNOWN
Classifier: Development Status :: 3 - Alpha
Classifier: Programming Language :: Python :: 3
Classifier: Programming Language :: Python :: 3.7
Classifier: License :: OSI Approved :: MIT License
Classifier: Operating System :: Microsoft :: Windows
Classifier: Operating System :: POSIX :: Linux
Requires-Dist: pybind11 (>=2.2)
